litedbc/__init__.py
litedbc/__main__.py
litedbc/const/__init__.py
litedbc/cursor/__init__.py
litedbc/errors/__init__.py
litedbc/misc/__init__.py
litedbc/transaction/__init__.py
tests/__init__.py
tests/__main__.py
tests/test_dbc.py
litedbc-0.0.3.dist-info/LICENSE
litedbc-0.0.3.dist-info/METADATA
litedbc-0.0.3.dist-info/WHEEL
litedbc-0.0.3.dist-info/entry_points.txt
litedbc-0.0.3.dist-info/top_level.txt
litedbc-0.0.3.dist-info/RECORD
